design.sv
module ALU_4_bit( 
  input [3:0] A,
  input [3:0] B,
  input [2:0] Opcode,
  
  output reg [3:0] Output,
  output reg Carry_out,
  output reg zero
);
  
  
  always @(*)
    begin
      
      Carry_out = 0;
      
      case (Opcode)
        
        3'b000: begin
          
          {Carry_out, Output} = A + B;
          
        end
        
        
        3'b001: begin
          
          {Carry_out, Output} = A - B;
          
        end
      
        
        3'b010: begin
          
          Output = A & B;
          
        end
        
        
        3'b011: begin
          
          Output = A | B;
          
        end
        
        
        3'b100: begin
          
          Output = A ^ B;
          
        end
        
        
        3'b101: begin
          
          Output = ~A;
          
        end
        
        
        default: begin
          
          Output = 4'b0000;
          Carry_out = 0;
          
        end
        
      endcase
      
  
  
  if (Output == 4'b0000)
    zero = 1;
  else
    zero = 0;
  end
  
endmodule

testbench.sv
module ALU_4_bit_tb;
  
  reg [3:0] A;
  reg [3:0] B;
  reg [2:0] Opcode;
  
  wire [3:0] Output;
  wire Carry_out;
  wire zero;
  
  
  ALU_4_bit dut (
    .A(A),
    .B(B),
    .Opcode(Opcode),
    
    .Output(Output),
    .Carry_out(Carry_out),
    .zero(zero)
  );
  
  
  initial
    begin
      
    $dumpfile("dump.vcd"); 
    $dumpvars(0, ALU_4_bit_tb);
      
    end
  
  
  initial
    begin
      
      $display ("------------------------------------------------------");
      $display (" A     B    Opcode   Output    Carry_out   zero");
      $display ("------------------------------------------------------");
      $monitor (" %b   %b   %b   %b   %b   %b", 
                A, B, Opcode, Output, Carry_out, zero);
                          
      
      A = 4'b0001; B = 4'b1111; Opcode = 3'b000;
      #10;
                
      A = 4'b0001; B = 4'b1110; Opcode = 3'b000;
      #10;
                
      A = 4'b0001; B = 4'b1110; Opcode = 3'b001;
      #10;
                
      A = 4'b0001; B = 4'b1110; Opcode = 3'b010;
      #10;
                
      A = 4'b0001; B = 4'b1110; Opcode = 3'b011;
      #10;
                
      A = 4'b0001; B = 4'b1110; Opcode = 3'b100;
      #10;
                
      A = 4'b0001; B = 4'b1110; Opcode = 3'b101;
      #10;
                
      A = 4'b1010; B = 4'b1010; Opcode = 3'b001;
      #10;
                
      $finish;
                
    end
                
endmodule

dump.vcd
$date
	Fri May 22 21:40:39 2026
$end
$version
	Icarus Verilog
$end
$timescale
	1s
$end
$scope module ALU_4_bit_tb $end
$var wire 1 ! zero $end
$var wire 4 " Output [3:0] $end
$var wire 1 # Carry_out $end
$var reg 4 $ A [3:0] $end
$var reg 4 % B [3:0] $end
$var reg 3 & Opcode [2:0] $end
$scope module dut $end
$var wire 4 ' A [3:0] $end
$var wire 4 ( B [3:0] $end
$var wire 3 ) Opcode [2:0] $end
$var reg 1 # Carry_out $end
$var reg 4 * Output [3:0] $end
$var reg 1 ! zero $end
$upscope $end
$upscope $end
$enddefinitions $end
$comment Show the parameter values. $end
$dumpall
$end
#0
$dumpvars
b0 *
b0 )
b1111 (
b1 '
b0 &
b1111 %
b1 $
1#
b0 "
1!
$end
#10
0!
b1111 "
b1111 *
0#
b1110 %
b1110 (
#20
1#
b11 "
b11 *
b1 &
b1 )
#30
1!
b0 "
b0 *
0#
b10 &
b10 )
#40
0!
b1111 "
b1111 *
b11 &
b11 )
#50
b100 &
b100 )
#60
b1110 "
b1110 *
b101 &
b101 )
#70
1!
b0 "
b0 *
b1 &
b1 )
b1010 %
b1010 (
b1010 $
b1010 '
